{
  "rows": [
    {
      "engine": "browser-light",
      "split": "seen",
      "policy": "RL-before",
      "makespan": 354.1,
      "makespanSd": 22.735214975891473,
      "completeRate": 100,
      "soft": 4.5,
      "hardExecuted": 0,
      "hardMask": 7.6,
      "travel": 28.312122882108536,
      "setup": 200,
      "move": 226.4969830568683
    },
    {
      "engine": "browser-light",
      "split": "seen",
      "policy": "MAPPO-trained",
      "makespan": 283.4,
      "makespanSd": 26.993332510084784,
      "completeRate": 100,
      "soft": 2.9,
      "hardExecuted": 0,
      "hardMask": 2.3,
      "travel": 20.142483006739088,
      "setup": 106,
      "move": 161.1398640539127
    },
    {
      "engine": "browser-light",
      "split": "seen",
      "policy": "Nearest",
      "makespan": 336.4,
      "makespanSd": 30.345345606863667,
      "completeRate": 100,
      "soft": 6.7,
      "hardExecuted": 0,
      "hardMask": 7.2,
      "travel": 21.262703103809905,
      "setup": 150,
      "move": 170.10162483047924
    },
    {
      "engine": "browser-light",
      "split": "seen",
      "policy": "Same-radius",
      "makespan": 336.4,
      "makespanSd": 30.345345606863667,
      "completeRate": 100,
      "soft": 6.7,
      "hardExecuted": 0,
      "hardMask": 7.2,
      "travel": 21.262703103809905,
      "setup": 150,
      "move": 170.10162483047924
    },
    {
      "engine": "browser-light",
      "split": "seen",
      "policy": "Random",
      "makespan": 457,
      "makespanSd": 78.58371332534496,
      "completeRate": 100,
      "soft": 6.3,
      "hardExecuted": 0,
      "hardMask": 21.2,
      "travel": 47.62866739822042,
      "setup": 185,
      "move": 381.0293391857634
    },
    {
      "engine": "browser-light",
      "split": "unseen",
      "policy": "RL-before",
      "makespan": 362.43333333333334,
      "makespanSd": 47.20147125767256,
      "completeRate": 100,
      "soft": 5.366666666666666,
      "hardExecuted": 0,
      "hardMask": 8.733333333333333,
      "travel": 28.191797738893836,
      "setup": 201,
      "move": 225.5343819111507
    },
    {
      "engine": "browser-light",
      "split": "unseen",
      "policy": "MAPPO-trained",
      "makespan": 294.8333333333333,
      "makespanSd": 34.029480683013006,
      "completeRate": 100,
      "soft": 2.933333333333333,
      "hardExecuted": 0,
      "hardMask": 3.6,
      "travel": 19.79182820242362,
      "setup": 106.66666666666667,
      "move": 158.33462561938896
    },
    {
      "engine": "browser-light",
      "split": "unseen",
      "policy": "Nearest",
      "makespan": 358.5,
      "makespanSd": 72.66853973121151,
      "completeRate": 100,
      "soft": 7.6,
      "hardExecuted": 0,
      "hardMask": 9.233333333333333,
      "travel": 19.48658712703352,
      "setup": 144.66666666666666,
      "move": 155.89269701626816
    },
    {
      "engine": "browser-light",
      "split": "unseen",
      "policy": "Same-radius",
      "makespan": 358.5,
      "makespanSd": 72.66853973121151,
      "completeRate": 100,
      "soft": 7.6,
      "hardExecuted": 0,
      "hardMask": 9.233333333333333,
      "travel": 19.48658712703352,
      "setup": 144.66666666666666,
      "move": 155.89269701626816
    },
    {
      "engine": "browser-light",
      "split": "unseen",
      "policy": "Random",
      "makespan": 470.8333333333333,
      "makespanSd": 72.55208856783901,
      "completeRate": 100,
      "soft": 5.766666666666667,
      "hardExecuted": 0,
      "hardMask": 22.4,
      "travel": 44.1024266442936,
      "setup": 174,
      "move": 352.8194131543488
    },
    {
      "engine": "pytorch-repeated-aggregate",
      "split": "seen",
      "policy": "PyTorch MAPPO",
      "makespan": 316.56226666666663,
      "makespanSd": 0,
      "completeRate": 0,
      "soft": 0,
      "hardExecuted": 0,
      "hardMask": 0,
      "travel": 0,
      "setup": 0,
      "move": 0
    },
    {
      "engine": "pytorch-repeated-aggregate",
      "split": "unseen",
      "policy": "PyTorch MAPPO",
      "makespan": 327.32634444444443,
      "makespanSd": 12.728287273637662,
      "completeRate": 100.0,
      "soft": 0,
      "hardExecuted": 0.0,
      "hardMask": 15.31111111111111,
      "travel": 0,
      "setup": 0,
      "move": 0
    },
    {
      "engine": "pytorch-run",
      "split": "seen",
      "policy": "group1_train101-110_unseen201-230",
      "makespan": 313.65119999999996,
      "makespanSd": 29.948526273591494,
      "completeRate": 100.0,
      "soft": 6.6,
      "hardExecuted": 0.0,
      "hardMask": 12.7,
      "travel": 0,
      "setup": 0,
      "move": 0
    },
    {
      "engine": "pytorch-run",
      "split": "unseen",
      "policy": "group1_train101-110_unseen201-230",
      "makespan": 342.8796333333333,
      "makespanSd": 54.93049918850992,
      "completeRate": 100.0,
      "soft": 5.633333333333334,
      "hardExecuted": 0.0,
      "hardMask": 15.933333333333334,
      "travel": 15.789021387998366,
      "setup": 113.66666666666667,
      "move": 157.89021387998363
    },
    {
      "engine": "pytorch-run",
      "split": "seen",
      "policy": "group2_train111-120_unseen231-260",
      "makespan": 337.2474,
      "makespanSd": 45.775250214936015,
      "completeRate": 100.0,
      "soft": 3.7,
      "hardExecuted": 0.0,
      "hardMask": 14.1,
      "travel": 0,
      "setup": 0,
      "move": 0
    },
    {
      "engine": "pytorch-run",
      "split": "unseen",
      "policy": "group2_train111-120_unseen231-260",
      "makespan": 327.39733333333334,
      "makespanSd": 51.606306478526015,
      "completeRate": 100.0,
      "soft": 5.0,
      "hardExecuted": 0.0,
      "hardMask": 13.733333333333333,
      "travel": 18.247785149187777,
      "setup": 115.33333333333333,
      "move": 182.47785149187771
    },
    {
      "engine": "pytorch-run",
      "split": "seen",
      "policy": "group3_train121-130_unseen261-290",
      "makespan": 298.78819999999996,
      "makespanSd": 31.285259905584933,
      "completeRate": 100.0,
      "soft": 6.0,
      "hardExecuted": 0.0,
      "hardMask": 10.8,
      "travel": 0,
      "setup": 0,
      "move": 0
    },
    {
      "engine": "pytorch-run",
      "split": "unseen",
      "policy": "group3_train121-130_unseen261-290",
      "makespan": 311.70206666666667,
      "makespanSd": 42.60063976118459,
      "completeRate": 100.0,
      "soft": 5.433333333333334,
      "hardExecuted": 0.0,
      "hardMask": 16.266666666666666,
      "travel": 17.613655148948855,
      "setup": 99.0,
      "move": 176.13655148948854
    }
  ],
  "comparison": {
    "notes": [
      "Browser-light MAPPO는 브라우저 내 구조/시각화 검증용 경량 구현이다.",
      "PyTorch MAPPO는 분리된 연구용 학습 엔진이다.",
      "두 결과는 scenario generator를 정합화했더라도 학습 업데이트/후보 scoring/저장된 모델 시점이 다를 수 있어 직접 우열보다 역할 분리와 공정 조건 확인이 중요하다."
    ],
    "browser_unseen_mappo_makespan": 294.8333333333333,
    "pytorch_unseen_mappo_makespan": 327.32634444444443,
    "pytorch_vs_browser_unseen_delta": 32.493011111111116
  }
}